pydatasource/DataSource.py
pydatasource/__init__.py
pydatasource/core/__init__.py
pydatasource/core/documentation.py
pydatasource/core/environment_comparison.py
pydatasource/core/snippet.py
pydatasource-0.1.6.dist-info/LICENSE
pydatasource-0.1.6.dist-info/METADATA
pydatasource-0.1.6.dist-info/WHEEL
pydatasource-0.1.6.dist-info/top_level.txt
pydatasource-0.1.6.dist-info/RECORD
