Metadata-Version: 2.1
Name: pydatasource
Version: 0.1.6
Summary: Easily manage a dataflow
Home-page: https://github.com/dacker-team/pydatasource
Author: Dacker
Author-email: hello@dacker.co
License: UNKNOWN
Keywords: easily manage dataflow
Platform: UNKNOWN
Classifier: Programming Language :: Python :: 3
Classifier: License :: OSI Approved :: MIT License
Classifier: Operating System :: OS Independent
Requires-Python: >=3
Requires-Dist: dbstream (>=0.0.20)
Requires-Dist: PyYAML (>=5.1.2)
Requires-Dist: tabulate (>=0.8.7)
Requires-Dist: dacktool (>=0.0.7)
